odoo8_addon_l10n_es_payment_order_confirminet-8.0.1.0.0.99.dev12-py3.6-nspkg.pth
odoo_addons/l10n_es_payment_order_confirminet/README.rst
odoo_addons/l10n_es_payment_order_confirminet/__init__.py
odoo_addons/l10n_es_payment_order_confirminet/__openerp__.py
odoo_addons/l10n_es_payment_order_confirminet/data/payment_type_data.xml
odoo_addons/l10n_es_payment_order_confirminet/i18n/ca.po
odoo_addons/l10n_es_payment_order_confirminet/i18n/es.po
odoo_addons/l10n_es_payment_order_confirminet/i18n/fr.po
odoo_addons/l10n_es_payment_order_confirminet/i18n/l10n_es_payment_order_confirminet.pot
odoo_addons/l10n_es_payment_order_confirminet/i18n/nl.po
odoo_addons/l10n_es_payment_order_confirminet/i18n/pt_BR.po
odoo_addons/l10n_es_payment_order_confirminet/i18n/sl.po
odoo_addons/l10n_es_payment_order_confirminet/models/__init__.py
odoo_addons/l10n_es_payment_order_confirminet/models/payment_mode.py
odoo_addons/l10n_es_payment_order_confirminet/static/description/icon.png
odoo_addons/l10n_es_payment_order_confirminet/static/description/icon_src.svg
odoo_addons/l10n_es_payment_order_confirminet/views/payment_mode_view.xml
odoo_addons/l10n_es_payment_order_confirminet/wizard/__init__.py
odoo_addons/l10n_es_payment_order_confirminet/wizard/confirminet.py
odoo_addons/l10n_es_payment_order_confirminet/wizard/export_csb.py
odoo8_addon_l10n_es_payment_order_confirminet-8.0.1.0.0.99.dev12.dist-info/METADATA
odoo8_addon_l10n_es_payment_order_confirminet-8.0.1.0.0.99.dev12.dist-info/WHEEL
odoo8_addon_l10n_es_payment_order_confirminet-8.0.1.0.0.99.dev12.dist-info/namespace_packages.txt
odoo8_addon_l10n_es_payment_order_confirminet-8.0.1.0.0.99.dev12.dist-info/top_level.txt
odoo8_addon_l10n_es_payment_order_confirminet-8.0.1.0.0.99.dev12.dist-info/RECORD
